{
  "type": "Feature",
  "properties": {
    "gn:admin1_code":"0.0",
    "gn:asciiname":"Faleasi`u",
    "gn:country_code":"WS",
    "gn:dem":10,
    "gn:feature_class":"P",
    "gn:feature_code":"PPL",
    "gn:name":"Faleasi\u2018u",
    "gn:population":0,
    "gn:timezone":"Pacific/Apia",
    "iso:country":"WS",
    "wof:name":"Faleasi`u",
    "wof:placetype":"locality"
},
  "geometry": {"coordinates":[-171.92864,-13.80742],"type":"Point"}
}