{
  "type": "Feature",
  "properties": {
    "gn:admin1_code":"0.0",
    "gn:asciiname":"Le Piu Uta",
    "gn:country_code":"WS",
    "gn:dem":119,
    "gn:feature_class":"P",
    "gn:feature_code":"PPL",
    "gn:name":"Le Piu Uta",
    "gn:population":0,
    "gn:timezone":"Pacific/Apia",
    "iso:country":"WS",
    "wof:name":"Le Piu Uta",
    "wof:placetype":"locality"
},
  "geometry": {"coordinates":[-172.38144,-13.46363],"type":"Point"}
}