{
  "type": "Feature",
  "properties": {
    "gn:country":"WS",
    "gn:fcode":"PPL",
    "gn:population":228,
    "iso:country":"WS",
    "qs:name":"Tapueleele",
    "qs:photos_9r":0,
    "qs:photos_sr":0,
    "qs:pop_sr":"2",
    "wof:name":"Tapueleele",
    "wof:placetype":"locality",
    "wof:population":228
},
  "geometry": {"coordinates":[-172.23622,-13.64675],"type":"Point"}
}