{
  "type": "Feature",
  "properties": {
    "gn:country":"WS",
    "gn:fcode":"PPL",
    "gn:pop":877,
    "iso:country":"WS",
    "name:dut_x_preferred":[
        "Sapapali'i"
    ],
    "name:eng_x_preferred":[
        "Sapapali'i"
    ],
    "qs:name":"Sapapali\u2019i",
    "qs:photos_9r":0,
    "qs:photos_sr":0,
    "qs:pop_sr":"2",
    "wd:wordcount":202,
    "wof:name":"Sapapali\u2019i",
    "wof:placetype":"locality",
    "wof:population":877
},
  "geometry": {"coordinates":[-172.1918,-13.68726],"type":"Point"}
}