{
  "type": "Feature",
  "properties": {
    "gn:admin1_code":"0.0",
    "gn:asciiname":"Vailavea",
    "gn:country_code":"WS",
    "gn:dem":10,
    "gn:feature_class":"P",
    "gn:feature_code":"PPL",
    "gn:name":"Vailavea",
    "gn:population":0,
    "gn:timezone":"Pacific/Apia",
    "iso:country":"WS",
    "wof:name":"Vailavea",
    "wof:placetype":"locality"
},
  "geometry": {"coordinates":[-172.05373,-13.90256],"type":"Point"}
}