{
  "type": "Feature",
  "properties": {
    "gn:admin1_code":"0.0",
    "gn:asciiname":"Lu'ua",
    "gn:country_code":"WS",
    "gn:dem":11,
    "gn:feature_class":"P",
    "gn:feature_code":"PPL",
    "gn:name":"Lu\u2019ua",
    "gn:population":0,
    "gn:timezone":"Pacific/Apia",
    "iso:country":"WS",
    "wof:name":"Lu'ua",
    "wof:placetype":"locality"
},
  "geometry": {"coordinates":[-172.18773999999999,-13.65279],"type":"Point"}
}