{
  "type": "Feature",
  "properties": {
    "gn:admin1_code":"0.0",
    "gn:asciiname":"Salesulumua",
    "gn:country_code":"WS",
    "gn:dem":8,
    "gn:feature_class":"P",
    "gn:feature_code":"PPL",
    "gn:name":"Salesulumua",
    "gn:population":0,
    "gn:timezone":"Pacific/Apia",
    "iso:country":"WS",
    "wof:name":"Salesulumua",
    "wof:placetype":"locality"
},
  "geometry": {"coordinates":[-171.96666999999999,-13.81667],"type":"Point"}
}