{
  "type": "Feature",
  "properties": {
    "gn:country":"WS",
    "gn:fcode":"PPL",
    "gn:population":648,
    "iso:country":"WS",
    "name:eng_x_preferred":[
        "Siutu"
    ],
    "name:jpn_x_preferred":[
        "\u30b7\u30a6\u30c4"
    ],
    "name:nld_x_preferred":[
        "Siutu"
    ],
    "name:slk_x_preferred":[
        "Siutu"
    ],
    "name:smo_x_preferred":[
        "Siutu"
    ],
    "qs:name":"Siutu",
    "qs:photos_9r":0,
    "qs:photos_sr":0,
    "qs:pop_sr":"2",
    "wd:wordcount":92,
    "wof:name":"Siutu",
    "wof:placetype":"locality",
    "wof:population":648
},
  "geometry": {"coordinates":[-172.59540999999999,-13.72099],"type":"Point"}
}