{
  "type": "Feature",
  "properties": {
    "gn:admin1_code":"0.0",
    "gn:asciiname":"Sogi",
    "gn:country_code":"WS",
    "gn:dem":11,
    "gn:feature_class":"P",
    "gn:feature_code":"PPL",
    "gn:name":"Sogi",
    "gn:population":0,
    "gn:timezone":"Pacific/Apia",
    "iso:country":"WS",
    "name:und_x_variant":[
        "Songi",
        "Sogi"
    ],
    "wof:name":"Sogi",
    "wof:placetype":"locality"
},
  "geometry": {"coordinates":[-171.77373,-13.82837],"type":"Point"}
}