{
  "type": "Feature",
  "properties": {
    "gn:gn_country":"WS",
    "gn:gn_fcode":"PPL",
    "gn:gn_pop":1412,
    "gn:population":1412,
    "iso:country":"WS",
    "name:bul_x_preferred":[
        "\u0421\u0430\u0442\u0430\u043f\u0443\u0430\u043b\u0430"
    ],
    "name:eng_x_preferred":[
        "Satapuala"
    ],
    "name:nld_x_preferred":[
        "Satapuala"
    ],
    "qs_pg:aaroncc":"WS",
    "qs_pg:gn_country":"WS",
    "qs_pg:gn_fcode":"PPL",
    "qs_pg:gn_pop":1412,
    "qs_pg:name":"Satapuala",
    "qs_pg:photos_9r":0,
    "qs_pg:photos_sr":0,
    "qs_pg:pop_sr":3,
    "qs_pg:qs_pg_placetype":"locality",
    "wof:name":"Satapuala",
    "wof:placetype":"locality",
    "wof:population":1412
},
  "geometry": {"coordinates":[-171.97962999999999,-13.83535],"type":"Point"}
}