{
  "type": "Feature",
  "properties": {
    "gn:admin1_code":"10.0",
    "gn:asciiname":"Lalovaea",
    "gn:country_code":"WS",
    "gn:dem":16,
    "gn:feature_class":"P",
    "gn:feature_code":"PPL",
    "gn:name":"Lalovaea",
    "gn:population":0,
    "gn:timezone":"Pacific/Apia",
    "iso:country":"WS",
    "wof:name":"Lalovaea",
    "wof:placetype":"locality"
},
  "geometry": {"coordinates":[-171.76664,-13.83987],"type":"Point"}
}