{
  "type": "Feature",
  "properties": {
    "gn:admin1_code":"0.0",
    "gn:asciiname":"Manunu",
    "gn:country_code":"WS",
    "gn:dem":155,
    "gn:feature_class":"P",
    "gn:feature_code":"PPL",
    "gn:name":"Manunu",
    "gn:population":0,
    "gn:timezone":"Pacific/Apia",
    "iso:country":"WS",
    "wof:name":"Manunu",
    "wof:placetype":"locality"
},
  "geometry": {"coordinates":[-171.61792,-13.91604],"type":"Point"}
}