{
  "type": "Feature",
  "properties": {
    "gn:admin1_code":"0.0",
    "gn:asciiname":"Satufiauta",
    "gn:country_code":"WS",
    "gn:dem":27,
    "gn:feature_class":"P",
    "gn:feature_code":"PPL",
    "gn:name":"Satufiauta",
    "gn:population":0,
    "gn:timezone":"Pacific/Apia",
    "iso:country":"WS",
    "wof:name":"Satufiauta",
    "wof:placetype":"locality"
},
  "geometry": {"coordinates":[-172.35228999999995,-13.75527],"type":"Point"}
}