{
  "type": "Feature",
  "properties": {
    "gn:country":"WS",
    "gn:fcode":"PPL",
    "gn:pop":150,
    "iso:country":"WS",
    "qs:name":"Samea",
    "qs:photos_9r":0,
    "qs:photos_sr":0,
    "qs:pop_sr":"1",
    "wd:wordcount":135,
    "wof:name":"Samea",
    "wof:placetype":"locality",
    "wof:population":150
},
  "geometry": {"coordinates":[-172.0411,-13.83758],"type":"Point"}
}