{
  "type": "Feature",
  "properties": {
    "gn:country":"WS",
    "gn:fcode":"PPL",
    "gn:population":150,
    "iso:country":"WS",
    "name:arg_x_preferred":[
        "Samea"
    ],
    "name:ast_x_preferred":[
        "\u200eSamea\u200e"
    ],
    "name:bul_x_preferred":[
        "Samea"
    ],
    "name:cat_x_preferred":[
        "Samea"
    ],
    "name:ceb_x_preferred":[
        "Samea"
    ],
    "name:deu_x_preferred":[
        "Samea"
    ],
    "name:eng_x_preferred":[
        "Samea"
    ],
    "name:epo_x_preferred":[
        "Samea"
    ],
    "name:eus_x_preferred":[
        "Samea"
    ],
    "name:ext_x_preferred":[
        "Samea"
    ],
    "name:fin_x_preferred":[
        "Samea"
    ],
    "name:fra_x_preferred":[
        "Samea"
    ],
    "name:gle_x_preferred":[
        "Samea"
    ],
    "name:glg_x_preferred":[
        "Samea"
    ],
    "name:ido_x_preferred":[
        "Samea"
    ],
    "name:ile_x_preferred":[
        "Samea"
    ],
    "name:ina_x_preferred":[
        "Samea"
    ],
    "name:ita_x_preferred":[
        "Samea"
    ],
    "name:lat_x_preferred":[
        "Samea"
    ],
    "name:nld_x_preferred":[
        "Samea"
    ],
    "name:oci_x_preferred":[
        "Samea"
    ],
    "name:pol_x_preferred":[
        "Samea"
    ],
    "name:por_x_preferred":[
        "Samea"
    ],
    "name:ron_x_preferred":[
        "Samea"
    ],
    "name:rus_x_preferred":[
        "Samea"
    ],
    "name:spa_x_preferred":[
        "Samea"
    ],
    "name:sqi_x_preferred":[
        "Samea"
    ],
    "name:swe_x_preferred":[
        "Samea"
    ],
    "name:ukr_x_preferred":[
        "Samea"
    ],
    "name:vie_x_preferred":[
        "Samea"
    ],
    "name:vol_x_preferred":[
        "Samea"
    ],
    "name:war_x_preferred":[
        "Samea"
    ],
    "qs:name":"Samea",
    "qs:photos_9r":0,
    "qs:photos_sr":0,
    "qs:pop_sr":"1",
    "wd:wordcount":135,
    "wof:name":"Samea",
    "wof:placetype":"locality",
    "wof:population":150
},
  "geometry": {"coordinates":[-172.0411,-13.83758],"type":"Point"}
}