{
  "type": "Feature",
  "properties": {
    "gn:country":"WS",
    "gn:fcode":"PPL",
    "gn:population":218,
    "iso:country":"WS",
    "name:ceb_x_preferred":[
        "Sa\u2019asa\u2019ai"
    ],
    "name:ell_x_preferred":[
        "\u039b\u03cc\u03bd\u03b1"
    ],
    "name:eng_x_preferred":[
        "Lona"
    ],
    "name:nld_x_preferred":[
        "Lona"
    ],
    "qs:name":"Lona",
    "qs:photos_9r":0,
    "qs:photos_sr":0,
    "qs:pop_sr":"2",
    "wd:wordcount":84,
    "wof:name":"Lona",
    "wof:placetype":"locality",
    "wof:population":218
},
  "geometry": {"coordinates":[-171.54292000000001,-13.94209],"type":"Point"}
}