{
  "type": "Feature",
  "properties": {
    "gn:admin1_code":"8.0",
    "gn:asciiname":"Foailalo",
    "gn:country_code":"WS",
    "gn:dem":42,
    "gn:feature_class":"P",
    "gn:feature_code":"PPL",
    "gn:name":"Foailalo",
    "gn:population":0,
    "gn:timezone":"Pacific/Apia",
    "iso:country":"WS",
    "name:slk_x_preferred":[
        "Foailalo"
    ],
    "name:und_x_variant":[
        "Foalelo",
        "Foa Lalo",
        "Foailalo"
    ],
    "wof:name":"Foailalo",
    "wof:placetype":"locality"
},
  "geometry": {"coordinates":[-172.60453000000001,-13.70226],"type":"Point"}
}