{
  "type": "Feature",
  "properties": {
    "gn:admin1_code":"0.0",
    "gn:asciiname":"Vailoa",
    "gn:country_code":"WS",
    "gn:dem":6,
    "gn:feature_class":"P",
    "gn:feature_code":"PPL",
    "gn:name":"Vailoa",
    "gn:population":336,
    "gn:timezone":"Pacific/Apia",
    "iso:country":"WS",
    "name:ceb_x_preferred":[
        "Vailoa"
    ],
    "name:deu_x_preferred":[
        "Vailoa"
    ],
    "name:mrj_x_preferred":[
        "\u0412\u0430\u0438\u043b\u043e\u0430"
    ],
    "name:slk_x_preferred":[
        "Vailoa"
    ],
    "name:urd_x_preferred":[
        "\u0648\u0627\u06cc\u0644\u0648\u0627"
    ],
    "wof:name":"Vailoa",
    "wof:placetype":"locality",
    "wof:population":336
},
  "geometry": {"coordinates":[-171.43534,-14.03888],"type":"Point"}
}