{
  "type": "Feature",
  "properties": {
    "gn:admin1_code":"0.0",
    "gn:asciiname":"Vaipapa",
    "gn:country_code":"WS",
    "gn:dem":193,
    "gn:feature_class":"P",
    "gn:feature_code":"PPL",
    "gn:name":"Vaipapa",
    "gn:population":0,
    "gn:timezone":"Pacific/Apia",
    "iso:country":"WS",
    "wof:name":"Vaipapa",
    "wof:placetype":"locality"
},
  "geometry": {"coordinates":[-171.99707000000001,-13.86051],"type":"Point"}
}