{
  "type": "Feature",
  "properties": {
    "gn:admin1_code":"0.0",
    "gn:asciiname":"Sapulu",
    "gn:country_code":"WS",
    "gn:dem":14,
    "gn:feature_class":"P",
    "gn:feature_code":"PPL",
    "gn:name":"Sapulu",
    "gn:population":0,
    "gn:timezone":"Pacific/Apia",
    "iso:country":"WS",
    "wof:name":"Sapulu",
    "wof:placetype":"locality"
},
  "geometry": {"coordinates":[-172.21648999999999,-13.7328],"type":"Point"}
}