{
  "type": "Feature",
  "properties": {
    "gn:country":"WS",
    "gn:fcode":"PPL",
    "gn:population":447,
    "iso:country":"WS",
    "name:deu_x_preferred":[
        "Fusi Ferro"
    ],
    "name:eng_x_preferred":[
        "Fusi"
    ],
    "name:ita_x_preferred":[
        "Fusi"
    ],
    "name:nld_x_preferred":[
        "Fusi"
    ],
    "qs:name":"Fusi",
    "qs:photos_9r":0,
    "qs:photos_sr":0,
    "qs:pop_sr":"2",
    "wd:wordcount":207,
    "wof:name":"Fusi",
    "wof:placetype":"locality",
    "wof:population":447
},
  "geometry": {"coordinates":[-171.82944000000001,-13.99591],"type":"Point"}
}