{
  "type": "Feature",
  "properties": {
    "gn:admin1_code":"0.0",
    "gn:asciiname":"Tanumalala",
    "gn:country_code":"WS",
    "gn:dem":358,
    "gn:feature_class":"P",
    "gn:feature_code":"PPL",
    "gn:name":"Tanumalala",
    "gn:population":0,
    "gn:timezone":"Pacific/Apia",
    "iso:country":"WS",
    "wof:name":"Tanumalala",
    "wof:placetype":"locality"
},
  "geometry": {"coordinates":[-171.94075000000001,-13.89451],"type":"Point"}
}