{
  "type": "Feature",
  "properties": {
    "gn:country":"WS",
    "gn:fcode":"PPL",
    "gn:pop":284,
    "iso:country":"WS",
    "name:unk_x_variant":[
        "Papa Uta"
    ],
    "qs:name":"Papa",
    "qs:photos_9r":0,
    "qs:photos_sr":0,
    "qs:pop_sr":"2",
    "wd:wordcount":287,
    "wof:name":"Papa",
    "wof:placetype":"locality",
    "wof:population":284
},
  "geometry": {"coordinates":[-172.71516,-13.53077],"type":"Point"}
}