{
  "type": "Feature",
  "properties": {
    "gn:country":"WS",
    "gn:fcode":"PPL",
    "gn:population":284,
    "iso:country":"WS",
    "name:bos_x_preferred":[
        "Papa"
    ],
    "name:cat_x_preferred":[
        "Papa"
    ],
    "name:ceb_x_preferred":[
        "Papa"
    ],
    "name:dan_x_preferred":[
        "Papa"
    ],
    "name:deu_x_preferred":[
        "Papa"
    ],
    "name:est_x_preferred":[
        "Papa"
    ],
    "name:fra_x_preferred":[
        "Papa"
    ],
    "name:heb_x_preferred":[
        "\u05e4\u05e4\u05d0"
    ],
    "name:ita_x_preferred":[
        "Papa"
    ],
    "name:lat_x_preferred":[
        "Papa"
    ],
    "name:nor_x_preferred":[
        "Papa"
    ],
    "name:por_x_preferred":[
        "Papa"
    ],
    "name:rus_x_preferred":[
        "\u041f\u0430\u043f\u0430"
    ],
    "name:slk_x_preferred":[
        "Papa"
    ],
    "name:spa_x_preferred":[
        "Papa"
    ],
    "name:srp_x_preferred":[
        "\u041f\u0430\u043f\u0430"
    ],
    "name:swe_x_preferred":[
        "Papa"
    ],
    "name:tgl_x_preferred":[
        "Papa"
    ],
    "name:tur_x_preferred":[
        "Papa"
    ],
    "name:ukr_x_preferred":[
        "\u041f\u0430\u043f\u0430"
    ],
    "name:und_x_variant":[
        "Papa Uta"
    ],
    "name:war_x_preferred":[
        "Papa"
    ],
    "qs:name":"Papa",
    "qs:photos_9r":0,
    "qs:photos_sr":0,
    "qs:pop_sr":"2",
    "wd:wordcount":287,
    "wof:name":"Papa",
    "wof:placetype":"locality",
    "wof:population":284
},
  "geometry": {"coordinates":[-172.71516,-13.53077],"type":"Point"}
}