{
  "type": "Feature",
  "properties": {
    "gn:admin1_code":"0.0",
    "gn:asciiname":"Letava",
    "gn:country_code":"WS",
    "gn:dem":296,
    "gn:feature_class":"P",
    "gn:feature_code":"PPL",
    "gn:name":"Letava",
    "gn:population":0,
    "gn:timezone":"Pacific/Apia",
    "iso:country":"WS",
    "name:chv_x_preferred":[
        "\u041b\u0435\u0442\u0430\u0432\u043a\u0430"
    ],
    "name:deu_x_preferred":[
        "Lietauka"
    ],
    "name:lit_x_preferred":[
        "Lietava"
    ],
    "name:nno_x_preferred":[
        "Lietava"
    ],
    "name:pol_x_preferred":[
        "Litawka"
    ],
    "name:rus_x_preferred":[
        "\u041b\u0435\u0442\u0430\u0443\u043a\u0430"
    ],
    "name:ukr_x_preferred":[
        "\u041b\u0435\u0442\u0430\u0432\u043a\u0430"
    ],
    "name:und_x_variant":[
        "Letava"
    ],
    "wof:name":"Letava",
    "wof:placetype":"locality"
},
  "geometry": {"coordinates":[-171.76566,-13.87812],"type":"Point"}
}