{
  "type": "Feature",
  "properties": {
    "gn:admin1_code":"10.0",
    "gn:asciiname":"Lotopa",
    "gn:country_code":"WS",
    "gn:dem":27,
    "gn:feature_class":"P",
    "gn:feature_code":"PPL",
    "gn:name":"Lotopa",
    "gn:population":0,
    "gn:timezone":"Pacific/Apia",
    "iso:country":"WS",
    "wof:name":"Lotopa",
    "wof:placetype":"locality"
},
  "geometry": {"coordinates":[-171.78703999999999,-13.8467],"type":"Point"}
}