{
  "type": "Feature",
  "properties": {
    "gn:admin1_code":"9.0",
    "gn:asciiname":"Samataiuta",
    "gn:country_code":"WS",
    "gn:dem":88,
    "gn:feature_class":"P",
    "gn:feature_code":"PPL",
    "gn:name":"Samataiuta",
    "gn:population":0,
    "gn:timezone":"Pacific/Apia",
    "iso:country":"WS",
    "wof:name":"Samataiuta",
    "wof:placetype":"locality"
},
  "geometry": {"coordinates":[-172.65725,-13.64926],"type":"Point"}
}