{
  "type": "Feature",
  "properties": {
    "gn:country":"WS",
    "gn:fcode":"PPL",
    "gn:pop":16,
    "iso:country":"WS",
    "qs:name":"Faleolo",
    "qs:photos_9r":0,
    "qs:photos_sr":0,
    "qs:pop_sr":"1",
    "wof:name":"Faleolo",
    "wof:placetype":"locality",
    "wof:population":16
},
  "geometry": {"coordinates":[-172.01499000000001,-13.82746],"type":"Point"}
}