{
  "type": "Feature",
  "properties": {
    "gn:country":"WS",
    "gn:fcode":"PPL",
    "gn:population":847,
    "iso:country":"WS",
    "qs:name":"Faleatiu",
    "qs:photos_9r":0,
    "qs:photos_sr":0,
    "qs:pop_sr":"2",
    "wof:name":"Faleatiu",
    "wof:placetype":"locality",
    "wof:population":847
},
  "geometry": {"coordinates":[-171.97895,-13.82885],"type":"Point"}
}