{
  "type": "Feature",
  "properties": {
    "iso:country":"WS",
    "name:ell_x_preferred":[
        "\u03a3\u03b1\u03c6\u03bf\u03c4\u03bf\u03c5\u03bb\u03b1\u03c6\u03ac\u03b9"
    ],
    "name:eng_x_preferred":[
        "Safotulafai"
    ],
    "name:jpn_x_preferred":[
        "\u30b5\u30d5\u30a9\u30c4\u30e9\u30d5\u30a1\u30a4"
    ],
    "name:mrj_x_preferred":[
        "\u0421\u0430\u0444\u043e\u0442\u0443\u043b\u0430\u0444\u0430\u0438"
    ],
    "name:nld_x_preferred":[
        "Safotulafai"
    ],
    "name:und_x_variant":[
        "Safotulafei"
    ],
    "name:urd_x_preferred":[
        "\u0633\u0641\u0648\u062a\u0644\u0641\u0627\u0626\u06cc"
    ],
    "qs:gn_country":"WS",
    "qs:gn_fcode":"PPL",
    "qs:gn_pop":0,
    "qs:name":"Safotulafai",
    "qs:name_adm0":"Samoa",
    "qs:name_adm1":"Fa`asaleleaga",
    "qs:photos":299,
    "qs:photos_1k":61,
    "qs:photos_9k":1,
    "qs:photos_9r":4,
    "qs:photos_all":299,
    "qs:photos_sr":5,
    "qs:placetype":"Town",
    "qs:pop_sr":"0",
    "qs:woe_adm0":23424992,
    "wd:wordcount":399,
    "wof:name":"Safotulafai",
    "wof:placetype":"locality"
},
  "geometry": {"coordinates":[-172.17768000000001,-13.67147],"type":"Point"}
}