{
  "type": "Feature",
  "properties": {
    "gn:admin1_code":"0.0",
    "gn:asciiname":"Talimatau",
    "gn:country_code":"WS",
    "gn:dem":36,
    "gn:feature_class":"P",
    "gn:feature_code":"PPL",
    "gn:name":"Talimatau",
    "gn:population":0,
    "gn:timezone":"Pacific/Apia",
    "iso:country":"WS",
    "wof:name":"Talimatau",
    "wof:placetype":"locality"
},
  "geometry": {"coordinates":[-171.79621,-13.84248],"type":"Point"}
}