{
  "type": "Feature",
  "properties": {
    "gn:admin1_code":"0.0",
    "gn:asciiname":"Saluafata",
    "gn:country_code":"WS",
    "gn:dem":12,
    "gn:feature_class":"P",
    "gn:feature_code":"PPL",
    "gn:name":"Saluafata",
    "gn:population":0,
    "gn:timezone":"Pacific/Apia",
    "iso:country":"WS",
    "wof:name":"Saluafata",
    "wof:placetype":"locality"
},
  "geometry": {"coordinates":[-171.60244,-13.87551],"type":"Point"}
}