{
  "type": "Feature",
  "properties": {
    "gn:admin1_code":"0.0",
    "gn:asciiname":"Casala",
    "gn:country_code":"WS",
    "gn:dem":212,
    "gn:feature_class":"P",
    "gn:feature_code":"PPL",
    "gn:name":"Casala",
    "gn:population":0,
    "gn:timezone":"Pacific/Apia",
    "iso:country":"WS",
    "wof:name":"Casala",
    "wof:placetype":"locality"
},
  "geometry": {"coordinates":[-171.93213,-13.85625],"type":"Point"}
}