{
  "type": "Feature",
  "properties": {
    "iso:country":"WS",
    "qs:gn_country":"WS",
    "qs:gn_fcode":"PPL",
    "qs:gn_pop":789,
    "qs:name":"Samalaeulu",
    "qs:name_adm0":"Samoa",
    "qs:name_adm1":"Gaga`emauga",
    "qs:photos":172,
    "qs:photos_1k":35,
    "qs:photos_9k":1,
    "qs:photos_9r":4,
    "qs:photos_all":172,
    "qs:photos_sr":4,
    "qs:placetype":"Town",
    "qs:pop_sr":"2",
    "qs:woe_adm0":23424992,
    "wof:name":"Samalaeulu",
    "wof:placetype":"locality",
    "wof:population":789
},
  "geometry": {"coordinates":[-172.30015,-13.50098],"type":"Point"}
}