{
  "type": "Feature",
  "properties": {
    "gn:country":"WS",
    "gn:fcode":"PPL",
    "gn:population":314,
    "iso:country":"WS",
    "qs:name":"Tafagamanu",
    "qs:photos_9r":0,
    "qs:photos_sr":0,
    "qs:pop_sr":"2",
    "wof:name":"Tafagamanu",
    "wof:placetype":"locality",
    "wof:population":314
},
  "geometry": {"coordinates":[-171.96025,-13.94818],"type":"Point"}
}