{
  "type": "Feature",
  "properties": {
    "gn:admin1_code":"0.0",
    "gn:asciiname":"Tafue",
    "gn:country_code":"WS",
    "gn:dem":172,
    "gn:feature_class":"P",
    "gn:feature_code":"PPL",
    "gn:name":"Tafue",
    "gn:population":0,
    "gn:timezone":"Pacific/Apia",
    "iso:country":"WS",
    "wof:name":"Tafue",
    "wof:placetype":"locality"
},
  "geometry": {"coordinates":[-171.92508999999995,-13.84314],"type":"Point"}
}