{
  "type": "Feature",
  "properties": {
    "gn:admin1_code":"0.0",
    "gn:asciiname":"Sasita",
    "gn:country_code":"WS",
    "gn:dem":57,
    "gn:feature_class":"P",
    "gn:feature_code":"PPL",
    "gn:name":"Sasita",
    "gn:population":0,
    "gn:timezone":"Pacific/Apia",
    "iso:country":"WS",
    "wof:name":"Sasita",
    "wof:placetype":"locality"
},
  "geometry": {"coordinates":[-171.56098,-14.0401],"type":"Point"}
}