{
  "type": "Feature",
  "properties": {
    "gn:country":"WS",
    "gn:fcode":"PPL",
    "gn:pop":520,
    "iso:country":"WS",
    "name:eng_x_preferred":[
        "Sa'asa'ai"
    ],
    "name:nld_x_preferred":[
        "Sa'asa'ai"
    ],
    "name:unk_x_variant":[
        "Sasaai"
    ],
    "qs:name":"Sa\u2019asa\u2019ai",
    "qs:photos_9r":0,
    "qs:photos_sr":0,
    "qs:pop_sr":"2",
    "wof:name":"Sa\u2019asa\u2019ai",
    "wof:placetype":"locality",
    "wof:population":520
},
  "geometry": {"coordinates":[-172.1942,-13.63714],"type":"Point"}
}