{
  "type": "Feature",
  "properties": {
    "gn:admin1_code":"0.0",
    "gn:asciiname":"Matanofo",
    "gn:country_code":"WS",
    "gn:dem":13,
    "gn:feature_class":"P",
    "gn:feature_code":"PPL",
    "gn:name":"Mat\u0101nofo",
    "gn:population":0,
    "gn:timezone":"Pacific/Apia",
    "iso:country":"WS",
    "wof:name":"Matanofo",
    "wof:placetype":"locality"
},
  "geometry": {"coordinates":[-172.00666000000001,-13.91598],"type":"Point"}
}