{
  "type": "Feature",
  "properties": {
    "gn:admin1_code":"0.0",
    "gn:asciiname":"Papa",
    "gn:country_code":"WS",
    "gn:dem":15,
    "gn:feature_class":"P",
    "gn:feature_code":"PPL",
    "gn:name":"Papa",
    "gn:population":0,
    "gn:timezone":"Pacific/Apia",
    "iso:country":"WS",
    "wof:name":"Papa",
    "wof:placetype":"locality"
},
  "geometry": {"coordinates":[-172.36515,-13.77202],"type":"Point"}
}