{
  "type": "Feature",
  "properties": {
    "gn:country":"WS",
    "gn:fcode":"PPL",
    "gn:pop":30,
    "iso:country":"WS",
    "qs:name":"Ili\u2019ili",
    "qs:photos_9r":0,
    "qs:photos_sr":0,
    "qs:pop_sr":"1",
    "wof:name":"Ili\u2019ili",
    "wof:placetype":"locality",
    "wof:population":30
},
  "geometry": {"coordinates":[-171.70410000000001,-14.03226],"type":"Point"}
}