{
  "type": "Feature",
  "properties": {
    "gn:admin1_code":"0.0",
    "gn:asciiname":"Fasito`otai",
    "gn:country_code":"WS",
    "gn:dem":11,
    "gn:feature_class":"P",
    "gn:feature_code":"PPL",
    "gn:name":"Fasito\u2018otai",
    "gn:population":0,
    "gn:timezone":"Pacific/Apia",
    "iso:country":"WS",
    "name:pol_x_preferred":[
        "Fasito\u02bbo Tai"
    ],
    "name:und_x_variant":[
        "Fasito\u2018otai"
    ],
    "wof:name":"Fasito`otai",
    "wof:placetype":"locality"
},
  "geometry": {"coordinates":[-171.96308999999999,-13.82568],"type":"Point"}
}