{
  "type": "Feature",
  "properties": {
    "gn:admin1_code":"0.0",
    "gn:asciiname":"Lepale",
    "gn:country_code":"WS",
    "gn:dem":384,
    "gn:feature_class":"P",
    "gn:feature_code":"PPL",
    "gn:name":"Lepale",
    "gn:population":0,
    "gn:timezone":"Pacific/Apia",
    "iso:country":"WS",
    "wof:name":"Lepale",
    "wof:placetype":"locality"
},
  "geometry": {"coordinates":[-171.91626000000005,-13.87385],"type":"Point"}
}