{
  "type": "Feature",
  "properties": {
    "gn:country":"WS",
    "gn:fcode":"PPL",
    "gn:population":171,
    "iso:country":"WS",
    "qs:name":"Vaipouli",
    "qs:photos_9r":0,
    "qs:photos_sr":0,
    "qs:pop_sr":"1",
    "wof:name":"Vaipouli",
    "wof:placetype":"locality",
    "wof:population":171
},
  "geometry": {"coordinates":[-172.36896999999999,-13.4657],"type":"Point"}
}