{
  "type": "Feature",
  "properties": {
    "gn:admin1_code":"0.0",
    "gn:asciiname":"Vaoala",
    "gn:country_code":"WS",
    "gn:dem":242,
    "gn:feature_class":"P",
    "gn:feature_code":"PPL",
    "gn:name":"Vaoala",
    "gn:population":0,
    "gn:timezone":"Pacific/Apia",
    "iso:country":"WS",
    "wof:name":"Vaoala",
    "wof:placetype":"locality"
},
  "geometry": {"coordinates":[-171.76338999999999,-13.87406],"type":"Point"}
}