{
  "type": "Feature",
  "properties": {
    "gn:admin1_code":"0.0",
    "gn:asciiname":"Tafa'igata",
    "gn:country_code":"WS",
    "gn:dem":168,
    "gn:feature_class":"P",
    "gn:feature_code":"PPL",
    "gn:name":"Tafa\u2019igata",
    "gn:population":0,
    "gn:timezone":"Pacific/Apia",
    "iso:country":"WS",
    "name:und_x_variant":[
        "Tafa\u2019igata"
    ],
    "wof:name":"Tafa'igata",
    "wof:placetype":"locality"
},
  "geometry": {"coordinates":[-171.83001000000004,-13.85089],"type":"Point"}
}