{
  "type": "Feature",
  "properties": {
    "gn:admin1_code":"0.0",
    "gn:asciiname":"Tanumapua",
    "gn:country_code":"WS",
    "gn:dem":208,
    "gn:feature_class":"P",
    "gn:feature_code":"PPL",
    "gn:name":"Tanumapua",
    "gn:population":0,
    "gn:timezone":"Pacific/Apia",
    "iso:country":"WS",
    "wof:name":"Tanumapua",
    "wof:placetype":"locality"
},
  "geometry": {"coordinates":[-171.82048999999995,-13.86272],"type":"Point"}
}