{
  "type": "Feature",
  "properties": {
    "gn:admin1_code":"0.0",
    "gn:asciiname":"Nafanua",
    "gn:country_code":"WS",
    "gn:dem":117,
    "gn:feature_class":"P",
    "gn:feature_code":"PPL",
    "gn:name":"Nafanua",
    "gn:population":0,
    "gn:timezone":"Pacific/Apia",
    "iso:country":"WS",
    "name:deu_x_preferred":[
        "Nafanua"
    ],
    "name:lat_x_preferred":[
        "Nafanua"
    ],
    "wof:name":"Nafanua",
    "wof:placetype":"locality"
},
  "geometry": {"coordinates":[-171.76306,-13.85598],"type":"Point"}
}