{
  "type": "Feature",
  "properties": {
    "gn:admin1_code":"0.0",
    "gn:asciiname":"Togitogiga",
    "gn:country_code":"WS",
    "gn:dem":37,
    "gn:feature_class":"P",
    "gn:feature_code":"PPL",
    "gn:name":"Togitogiga",
    "gn:population":0,
    "gn:timezone":"Pacific/Apia",
    "iso:country":"WS",
    "wof:name":"Togitogiga",
    "wof:placetype":"locality"
},
  "geometry": {"coordinates":[-171.72094999999999,-14.01684],"type":"Point"}
}